func_hooks/__init__.py
func_hooks/decorator.py
func_hooks/exceptions.py
func_hooks/handler_list.py
func_hooks/py.typed
func_hooks/sync.py
func_hooks/typing.py
func_hooks-1.2.0.dist-info/METADATA
func_hooks-1.2.0.dist-info/WHEEL
func_hooks-1.2.0.dist-info/RECORD
