Metadata-Version: 2.1
Name: func-hooks
Version: 1.2.0
Summary: 
Author: Francisco Del Roio
Author-email: francipvb@hotmail.com
Requires-Python: >=3.8,<4.0
Classifier: Programming Language :: Python :: 3
Classifier: Programming Language :: Python :: 3.8
Classifier: Programming Language :: Python :: 3.9
Classifier: Programming Language :: Python :: 3.10
Classifier: Programming Language :: Python :: 3.11
Requires-Dist: anyio (>=3.6.2,<4.0.0)
Requires-Dist: typing-extensions (>=4.4.0,<5.0.0)
